clara/viz/widgets/VERSION
clara/viz/widgets/__init__.py
clara/viz/widgets/_version.py
clara/viz/widgets/widget.py
clara_viz_widgets-0.4.2.data/data/etc/jupyter/nbconfig/notebook.d/clara-viz-widgets.json
clara_viz_widgets-0.4.2.data/data/share/jupyter/labextensions/clara-viz-widgets/install.json
clara_viz_widgets-0.4.2.data/data/share/jupyter/labextensions/clara-viz-widgets/package.json
clara_viz_widgets-0.4.2.data/data/share/jupyter/labextensions/clara-viz-widgets/static/212.f871991b23241fdb80fe.js
clara_viz_widgets-0.4.2.data/data/share/jupyter/labextensions/clara-viz-widgets/static/212.f871991b23241fdb80fe.js.LICENSE.txt
clara_viz_widgets-0.4.2.data/data/share/jupyter/labextensions/clara-viz-widgets/static/261.a9760df2edd7a765ec62.js
clara_viz_widgets-0.4.2.data/data/share/jupyter/labextensions/clara-viz-widgets/static/486.7bf5fe6dcd49349f1e76.js
clara_viz_widgets-0.4.2.data/data/share/jupyter/labextensions/clara-viz-widgets/static/486.7bf5fe6dcd49349f1e76.js.LICENSE.txt
clara_viz_widgets-0.4.2.data/data/share/jupyter/labextensions/clara-viz-widgets/static/568.4b59d83749824b05d541.js
clara_viz_widgets-0.4.2.data/data/share/jupyter/labextensions/clara-viz-widgets/static/remoteEntry.b4d988bb8b5e80ab2248.js
clara_viz_widgets-0.4.2.data/data/share/jupyter/labextensions/clara-viz-widgets/static/style.js
clara_viz_widgets-0.4.2.data/data/share/jupyter/labextensions/clara-viz-widgets/static/third-party-licenses.json
clara_viz_widgets-0.4.2.data/data/share/jupyter/nbextensions/clara-viz-widgets/extension.js
clara_viz_widgets-0.4.2.data/data/share/jupyter/nbextensions/clara-viz-widgets/index.js
clara_viz_widgets-0.4.2.data/data/share/jupyter/nbextensions/clara-viz-widgets/index.js.LICENSE.txt
clara_viz_widgets-0.4.2.dist-info/licenses/LICENSE
clara_viz_widgets-0.4.2.dist-info/METADATA
clara_viz_widgets-0.4.2.dist-info/WHEEL
clara_viz_widgets-0.4.2.dist-info/top_level.txt
clara_viz_widgets-0.4.2.dist-info/RECORD
