Metadata-Version: 2.4
Name: clara-viz-widgets
Version: 0.4.2
Summary: A toolkit to provide GPU accelerated visualization of medical data.
Home-page: https://github.com/NVIDIA/clara-viz
Author: NVIDIA Corporation
License: Apache-2.0
Keywords: ipython,jupyter,widgets
Platform: manylinux_2_28_x86_64
Classifier: Development Status :: 4 - Beta
Classifier: Framework :: IPython
Classifier: Intended Audience :: Developers
Classifier: Intended Audience :: Science/Research
Classifier: Topic :: Multimedia :: Graphics
Classifier: Programming Language :: Python :: 3
Classifier: Programming Language :: Python :: 3.9
Classifier: Programming Language :: Python :: 3.10
Classifier: Programming Language :: Python :: 3.11
Classifier: Programming Language :: Python :: 3.12
Requires-Python: >= 3.9, < 3.13
License-File: LICENSE
Requires-Dist: packaging
Requires-Dist: clara-viz-core==0.4.2
Requires-Dist: ipywidgets<8.0,>=7.6.0
Dynamic: author
Dynamic: classifier
Dynamic: description
Dynamic: description-content-type
Dynamic: home-page
Dynamic: keywords
Dynamic: license
Dynamic: license-file
Dynamic: platform
Dynamic: requires-dist
Dynamic: requires-python
Dynamic: summary
